esser/__init__.py
esser/constants.py
esser/entities.py
esser/events.py
esser/exceptions.py
esser/reducer.py
esser/registry.py
esser/utils.py
esser/validators.py
esser-0.1.1.dist-info/DESCRIPTION.rst
esser-0.1.1.dist-info/METADATA
esser-0.1.1.dist-info/RECORD
esser-0.1.1.dist-info/WHEEL
esser-0.1.1.dist-info/metadata.json
esser-0.1.1.dist-info/top_level.txt
