Metadata-Version: 2.0
Name: esser
Version: 0.1.1
Summary: Python Event Sourcing framework
Home-page: https://geeknam.github.io/esser
Author: Nam Ngo
Author-email: namngology@gmail.com
License: Apache 2.0
Keywords: event sourcing,framework,esser,serverless,dynamodb,lambda
Platform: UNKNOWN
Requires-Dist: cerberus
Requires-Dist: pynamodb
